decaf/DECAF.py
decaf/__init__.py
decaf/data.py
decaf/logger.py
decaf/version.py
decaf_synthetic_data-0.1.7.dist-info/LICENSE
decaf_synthetic_data-0.1.7.dist-info/METADATA
decaf_synthetic_data-0.1.7.dist-info/WHEEL
decaf_synthetic_data-0.1.7.dist-info/top_level.txt
decaf_synthetic_data-0.1.7.dist-info/RECORD
