Metadata-Version: 2.1
Name: decaf-synthetic-data
Version: 0.1.7
Summary: DEbiasing CAusal Fairness
Home-page: https://github.com/trentkyono/DECAF
Author: Trent Kyono
Author-email: 
License: BSD-3-Clause
Platform: UNKNOWN
Classifier: Programming Language :: Python :: 3
Classifier: Topic :: Scientific/Engineering :: Artificial Intelligence
Classifier: Intended Audience :: Healthcare Industry
Classifier: License :: OSI Approved :: BSD License
Classifier: Operating System :: OS Independent
License-File: LICENSE
Requires-Dist: loguru
Requires-Dist: networkx<3.0,>=2.0
Requires-Dist: numpy>=1.19
Requires-Dist: pandas
Requires-Dist: pytorch-lightning>=2.4
Requires-Dist: scikit-learn
Requires-Dist: scipy
Requires-Dist: torch>=1.9
Requires-Dist: torchtext>=0.10
Requires-Dist: xgboost
